undersort/__init__.py
undersort/config.py
undersort/logger.py
undersort/main.py
undersort/sorter.py
undersort-0.1.4.dist-info/METADATA
undersort-0.1.4.dist-info/WHEEL
undersort-0.1.4.dist-info/entry_points.txt
undersort-0.1.4.dist-info/licenses/LICENSE
undersort-0.1.4.dist-info/RECORD
