Metadata-Version: 2.4
Name: undersort
Version: 0.1.4
Summary: A tool to sort class methods by visibility (public, protected, private)
Project-URL: Homepage, https://github.com/kivicode/undersort
Project-URL: Repository, https://github.com/kivicode/undersort
Project-URL: Issues, https://github.com/kivicode/undersort/issues
Author-email: KiviCode <kivicode.dev@gmail.com>
License: MIT
License-File: LICENSE
Keywords: class-methods,code-formatter,linter,python,sorting
Classifier: Development Status :: 4 - Beta
Classifier: Intended Audience :: Developers
Classifier: License :: OSI Approved :: MIT License
Classifier: Programming Language :: Python :: 3
Classifier: Programming Language :: Python :: 3.8
Classifier: Programming Language :: Python :: 3.9
Classifier: Programming Language :: Python :: 3.10
Classifier: Programming Language :: Python :: 3.11
Classifier: Programming Language :: Python :: 3.12
Classifier: Topic :: Software Development :: Libraries :: Python Modules
Classifier: Topic :: Software Development :: Quality Assurance
Requires-Python: >=3.8
Requires-Dist: libcst>=1.1.0
Requires-Dist: rich>=13.0.0
